openskills/__init__.py
openskills/_version.py
openskills/agent.py
openskills/cli/__init__.py
openskills/cli/main.py
openskills/cli/commands/__init__.py
openskills/core/__init__.py
openskills/core/executor.py
openskills/core/manager.py
openskills/core/matcher.py
openskills/core/parser.py
openskills/core/skill.py
openskills/llm/__init__.py
openskills/llm/base.py
openskills/llm/openai_compat.py
openskills/llm/prompt_builder.py
openskills/loaders/__init__.py
openskills/loaders/file_loader.py
openskills/models/__init__.py
openskills/models/dependency.py
openskills/models/instruction.py
openskills/models/metadata.py
openskills/models/resource.py
openskills/sandbox/__init__.py
openskills/sandbox/client.py
openskills/sandbox/executor.py
openskills/sandbox/logger.py
openskills/sandbox/manager.py
openskills/utils/__init__.py
openskills/utils/frontmatter.py
openskills_sdk-0.0.8.dist-info/METADATA
openskills_sdk-0.0.8.dist-info/WHEEL
openskills_sdk-0.0.8.dist-info/entry_points.txt
openskills_sdk-0.0.8.dist-info/licenses/LICENSE
openskills_sdk-0.0.8.dist-info/RECORD
