Metadata-Version: 2.4
Name: openskills-sdk
Version: 0.0.8
Summary: An open-source Agent Skill framework implementing progressive disclosure architecture
Project-URL: Homepage, https://github.com/anthropics/openskills-sdk
Project-URL: Documentation, https://github.com/anthropics/openskills-sdk#readme
Project-URL: Repository, https://github.com/anthropics/openskills-sdk.git
Project-URL: Issues, https://github.com/anthropics/openskills-sdk/issues
Author: OpenSkills Contributors
License: Apache-2.0
License-File: LICENSE
Keywords: agent,ai,chatgpt,claude,llm,openai,skill
Classifier: Development Status :: 3 - Alpha
Classifier: Intended Audience :: Developers
Classifier: License :: OSI Approved :: Apache Software License
Classifier: Programming Language :: Python :: 3
Classifier: Programming Language :: Python :: 3.10
Classifier: Programming Language :: Python :: 3.11
Classifier: Programming Language :: Python :: 3.12
Classifier: Topic :: Scientific/Engineering :: Artificial Intelligence
Requires-Python: >=3.10
Requires-Dist: httpx>=0.25
Requires-Dist: pydantic>=2.0
Requires-Dist: pyyaml>=6.0
Requires-Dist: rich>=13.0
Requires-Dist: typer>=0.9
Provides-Extra: dev
Requires-Dist: pytest-asyncio>=0.23; extra == 'dev'
Requires-Dist: pytest>=8.0; extra == 'dev'
Requires-Dist: ruff>=0.1; extra == 'dev'
Provides-Extra: sandbox
Requires-Dist: httpx>=0.25; extra == 'sandbox'
